{"butterfly": {"list": ["E:\\opencv_svm_hog\\Resource\\train_images\\butterfly\\image_0001.jpg", "E:\\opencv_svm_hog\\Resource\\train_images\\butterfly\\image_0002.jpg", "E:\\opencv_svm_hog\\Resource\\train_images\\butterfly\\image_0003.jpg", "E:\\opencv_svm_hog\\Resource\\train_images\\butterfly\\image_0004.jpg", "E:\\opencv_svm_hog\\Resource\\train_images\\butterfly\\image_0005.jpg", "E:\\opencv_svm_hog\\Resource\\train_images\\butterfly\\image_0006.jpg", "E:\\opencv_svm_hog\\Resource\\train_images\\butterfly\\image_0007.jpg", "E:\\opencv_svm_hog\\Resource\\train_images\\butterfly\\image_0008.jpg", "E:\\opencv_svm_hog\\Resource\\train_images\\butterfly\\image_0009.jpg", "E:\\opencv_svm_hog\\Resource\\train_images\\butterfly\\image_0010.jpg", "E:\\opencv_svm_hog\\Resource\\train_images\\butterfly\\image_0011.jpg", "E:\\opencv_svm_hog\\Resource\\train_images\\butterfly\\image_0012.jpg", "E:\\opencv_svm_hog\\Resource\\train_images\\butterfly\\image_0013.jpg", "E:\\opencv_svm_hog\\Resource\\train_images\\butterfly\\image_0014.jpg", "E:\\opencv_svm_hog\\Resource\\train_images\\butterfly\\image_0015.jpg", "E:\\opencv_svm_hog\\Resource\\train_images\\butterfly\\image_0016.jpg", "E:\\opencv_svm_hog\\Resource\\train_images\\butterfly\\image_0017.jpg", "E:\\opencv_svm_hog\\Resource\\train_images\\butterfly\\image_0018.jpg", "E:\\opencv_svm_hog\\Resource\\train_images\\butterfly\\image_0019.jpg", "E:\\opencv_svm_hog\\Resource\\train_images\\butterfly\\image_0020.jpg", "E:\\opencv_svm_hog\\Resource\\train_images\\butterfly\\image_0021.jpg", "E:\\opencv_svm_hog\\Resource\\train_images\\butterfly\\image_0022.jpg", "E:\\opencv_svm_hog\\Resource\\train_images\\butterfly\\image_0023.jpg", "E:\\opencv_svm_hog\\Resource\\train_images\\butterfly\\image_0024.jpg", "E:\\opencv_svm_hog\\Resource\\train_images\\butterfly\\image_0025.jpg", "E:\\opencv_svm_hog\\Resource\\train_images\\butterfly\\image_0026.jpg", "E:\\opencv_svm_hog\\Resource\\train_images\\butterfly\\image_0027.jpg", "E:\\opencv_svm_hog\\Resource\\train_images\\butterfly\\image_0028.jpg", "E:\\opencv_svm_hog\\Resource\\train_images\\butterfly\\image_0029.jpg", "E:\\opencv_svm_hog\\Resource\\train_images\\butterfly\\image_0030.jpg", "E:\\opencv_svm_hog\\Resource\\train_images\\butterfly\\image_0031.jpg", "E:\\opencv_svm_hog\\Resource\\train_images\\butterfly\\image_0032.jpg", "E:\\opencv_svm_hog\\Resource\\train_images\\butterfly\\image_0033.jpg", "E:\\opencv_svm_hog\\Resource\\train_images\\butterfly\\image_0034.jpg", "E:\\opencv_svm_hog\\Resource\\train_images\\butterfly\\image_0035.jpg", "E:\\opencv_svm_hog\\Resource\\train_images\\butterfly\\image_0036.jpg", "E:\\opencv_svm_hog\\Resource\\train_images\\butterfly\\image_0037.jpg", "E:\\opencv_svm_hog\\Resource\\train_images\\butterfly\\image_0038.jpg", "E:\\opencv_svm_hog\\Resource\\train_images\\butterfly\\image_0039.jpg", "E:\\opencv_svm_hog\\Resource\\train_images\\butterfly\\image_0040.jpg", "E:\\opencv_svm_hog\\Resource\\train_images\\butterfly\\image_0041.jpg", "E:\\opencv_svm_hog\\Resource\\train_images\\butterfly\\image_0043.jpg", "E:\\opencv_svm_hog\\Resource\\train_images\\butterfly\\image_0044.jpg", "E:\\opencv_svm_hog\\Resource\\train_images\\butterfly\\image_0045.jpg", "E:\\opencv_svm_hog\\Resource\\train_images\\butterfly\\image_0046.jpg", "E:\\opencv_svm_hog\\Resource\\train_images\\butterfly\\image_0048.jpg", "E:\\opencv_svm_hog\\Resource\\train_images\\butterfly\\image_0049.jpg", "E:\\opencv_svm_hog\\Resource\\train_images\\butterfly\\image_0050.jpg"], "type": 2}, "scissors": {"list": ["E:\\opencv_svm_hog\\Resource\\train_images\\scissors\\imaeg_0031.jpg", "E:\\opencv_svm_hog\\Resource\\train_images\\scissors\\image_0001.jpg", "E:\\opencv_svm_hog\\Resource\\train_images\\scissors\\image_0002.jpg", "E:\\opencv_svm_hog\\Resource\\train_images\\scissors\\image_0003.jpg", "E:\\opencv_svm_hog\\Resource\\train_images\\scissors\\image_0004.jpg", "E:\\opencv_svm_hog\\Resource\\train_images\\scissors\\image_0005.png", "E:\\opencv_svm_hog\\Resource\\train_images\\scissors\\image_0006.jpg", "E:\\opencv_svm_hog\\Resource\\train_images\\scissors\\image_0007.jpg", "E:\\opencv_svm_hog\\Resource\\train_images\\scissors\\image_0009.jpg", "E:\\opencv_svm_hog\\Resource\\train_images\\scissors\\image_0010.jpg", "E:\\opencv_svm_hog\\Resource\\train_images\\scissors\\image_0011.jpg", "E:\\opencv_svm_hog\\Resource\\train_images\\scissors\\image_0012.jpg", "E:\\opencv_svm_hog\\Resource\\train_images\\scissors\\image_0013.jpg", "E:\\opencv_svm_hog\\Resource\\train_images\\scissors\\image_0014.jpg", "E:\\opencv_svm_hog\\Resource\\train_images\\scissors\\image_0015.jpg", "E:\\opencv_svm_hog\\Resource\\train_images\\scissors\\image_0016.jpg", "E:\\opencv_svm_hog\\Resource\\train_images\\scissors\\image_0017.jpg", "E:\\opencv_svm_hog\\Resource\\train_images\\scissors\\image_0018.jpg", "E:\\opencv_svm_hog\\Resource\\train_images\\scissors\\image_0019.jpg", "E:\\opencv_svm_hog\\Resource\\train_images\\scissors\\image_0020.jpg", "E:\\opencv_svm_hog\\Resource\\train_images\\scissors\\image_0021.jpg", "E:\\opencv_svm_hog\\Resource\\train_images\\scissors\\image_0022.jpg", "E:\\opencv_svm_hog\\Resource\\train_images\\scissors\\image_0023.jpg", "E:\\opencv_svm_hog\\Resource\\train_images\\scissors\\image_0024.jpg", "E:\\opencv_svm_hog\\Resource\\train_images\\scissors\\image_0025.jpg", "E:\\opencv_svm_hog\\Resource\\train_images\\scissors\\image_0026.jpg", "E:\\opencv_svm_hog\\Resource\\train_images\\scissors\\image_0027.jpg", "E:\\opencv_svm_hog\\Resource\\train_images\\scissors\\image_0028.jpg", "E:\\opencv_svm_hog\\Resource\\train_images\\scissors\\image_0029.jpg", "E:\\opencv_svm_hog\\Resource\\train_images\\scissors\\image_0030.jpg", "E:\\opencv_svm_hog\\Resource\\train_images\\scissors\\image_0031.jpg", "E:\\opencv_svm_hog\\Resource\\train_images\\scissors\\image_0032.jpg", "E:\\opencv_svm_hog\\Resource\\train_images\\scissors\\image_0033.jpg", "E:\\opencv_svm_hog\\Resource\\train_images\\scissors\\image_0034.jpg", "E:\\opencv_svm_hog\\Resource\\train_images\\scissors\\image_0035.jpg", "E:\\opencv_svm_hog\\Resource\\train_images\\scissors\\image_0036.jpg"], "type": 4}, "camera": {"list": ["E:\\opencv_svm_hog\\Resource\\train_images\\camera\\image_0001.jpg", "E:\\opencv_svm_hog\\Resource\\train_images\\camera\\image_00016.jpg", "E:\\opencv_svm_hog\\Resource\\train_images\\camera\\image_0002.jpg", "E:\\opencv_svm_hog\\Resource\\train_images\\camera\\image_0003.jpg", "E:\\opencv_svm_hog\\Resource\\train_images\\camera\\image_0004.jpg", "E:\\opencv_svm_hog\\Resource\\train_images\\camera\\image_0005.jpg", "E:\\opencv_svm_hog\\Resource\\train_images\\camera\\image_0006.jpg", "E:\\opencv_svm_hog\\Resource\\train_images\\camera\\image_0007.jpg", "E:\\opencv_svm_hog\\Resource\\train_images\\camera\\image_0008.jpg", "E:\\opencv_svm_hog\\Resource\\train_images\\camera\\image_0009.jpg", "E:\\opencv_svm_hog\\Resource\\train_images\\camera\\image_0010.jpg", "E:\\opencv_svm_hog\\Resource\\train_images\\camera\\image_0011.jpg", "E:\\opencv_svm_hog\\Resource\\train_images\\camera\\image_0012.jpg", "E:\\opencv_svm_hog\\Resource\\train_images\\camera\\image_0013.jpg", "E:\\opencv_svm_hog\\Resource\\train_images\\camera\\image_0014.jpg", "E:\\opencv_svm_hog\\Resource\\train_images\\camera\\image_0015.jpg", "E:\\opencv_svm_hog\\Resource\\train_images\\camera\\image_0018.jpg", "E:\\opencv_svm_hog\\Resource\\train_images\\camera\\image_0019.jpg", "E:\\opencv_svm_hog\\Resource\\train_images\\camera\\image_0020.jpg", "E:\\opencv_svm_hog\\Resource\\train_images\\camera\\image_0021.jpg", "E:\\opencv_svm_hog\\Resource\\train_images\\camera\\image_0022.jpg", "E:\\opencv_svm_hog\\Resource\\train_images\\camera\\image_0023.jpg", "E:\\opencv_svm_hog\\Resource\\train_images\\camera\\image_0024.jpg", "E:\\opencv_svm_hog\\Resource\\train_images\\camera\\image_0026.jpg", "E:\\opencv_svm_hog\\Resource\\train_images\\camera\\image_0027.jpg", "E:\\opencv_svm_hog\\Resource\\train_images\\camera\\image_0028.jpg", "E:\\opencv_svm_hog\\Resource\\train_images\\camera\\image_0029.jpg", "E:\\opencv_svm_hog\\Resource\\train_images\\camera\\image_0030.jpg", "E:\\opencv_svm_hog\\Resource\\train_images\\camera\\image_0031.jpg", "E:\\opencv_svm_hog\\Resource\\train_images\\camera\\image_0032.jpg", "E:\\opencv_svm_hog\\Resource\\train_images\\camera\\image_0033.jpg", "E:\\opencv_svm_hog\\Resource\\train_images\\camera\\image_0034.jpg", "E:\\opencv_svm_hog\\Resource\\train_images\\camera\\image_0035.jpg", "E:\\opencv_svm_hog\\Resource\\train_images\\camera\\image_0036.jpg", "E:\\opencv_svm_hog\\Resource\\train_images\\camera\\image_0037.jpg", "E:\\opencv_svm_hog\\Resource\\train_images\\camera\\image_0038.jpg", "E:\\opencv_svm_hog\\Resource\\train_images\\camera\\image_0040.jpg", "E:\\opencv_svm_hog\\Resource\\train_images\\camera\\image_0041.jpg", "E:\\opencv_svm_hog\\Resource\\train_images\\camera\\image_0042.jpg", "E:\\opencv_svm_hog\\Resource\\train_images\\camera\\image_0043.jpg", "E:\\opencv_svm_hog\\Resource\\train_images\\camera\\image_0044.jpg", "E:\\opencv_svm_hog\\Resource\\train_images\\camera\\image_0045.jpg", "E:\\opencv_svm_hog\\Resource\\train_images\\camera\\image_0046.jpg", "E:\\opencv_svm_hog\\Resource\\train_images\\camera\\image_0047.jpg", "E:\\opencv_svm_hog\\Resource\\train_images\\camera\\image_0048.jpg", "E:\\opencv_svm_hog\\Resource\\train_images\\camera\\image_0049.jpg", "E:\\opencv_svm_hog\\Resource\\train_images\\camera\\image_0050.jpg", "E:\\opencv_svm_hog\\Resource\\train_images\\camera\\image_0051.jpg", "E:\\opencv_svm_hog\\Resource\\train_images\\camera\\image_0052.jpg", "E:\\opencv_svm_hog\\Resource\\train_images\\camera\\image_0053.jpg", "E:\\opencv_svm_hog\\Resource\\train_images\\camera\\image_0054.jpg", "E:\\opencv_svm_hog\\Resource\\train_images\\camera\\image_0055.jpg", "E:\\opencv_svm_hog\\Resource\\train_images\\camera\\image_0056.jpg"], "type": 3}, "airplanes": {"list": ["E:\\opencv_svm_hog\\Resource\\train_images\\airplanes\\image_0001.jpg", "E:\\opencv_svm_hog\\Resource\\train_images\\airplanes\\image_0002.jpg", "E:\\opencv_svm_hog\\Resource\\train_images\\airplanes\\image_0003.jpg", "E:\\opencv_svm_hog\\Resource\\train_images\\airplanes\\image_0004.jpg", "E:\\opencv_svm_hog\\Resource\\train_images\\airplanes\\image_0005.jpg", "E:\\opencv_svm_hog\\Resource\\train_images\\airplanes\\image_0006.jpg", "E:\\opencv_svm_hog\\Resource\\train_images\\airplanes\\image_0007.jpg", "E:\\opencv_svm_hog\\Resource\\train_images\\airplanes\\image_0008.jpg", "E:\\opencv_svm_hog\\Resource\\train_images\\airplanes\\image_0009.jpg", "E:\\opencv_svm_hog\\Resource\\train_images\\airplanes\\image_0010.jpg", "E:\\opencv_svm_hog\\Resource\\train_images\\airplanes\\image_0011.jpg", "E:\\opencv_svm_hog\\Resource\\train_images\\airplanes\\image_0012.jpg", "E:\\opencv_svm_hog\\Resource\\train_images\\airplanes\\image_0013.jpg", "E:\\opencv_svm_hog\\Resource\\train_images\\airplanes\\image_0014.jpg", "E:\\opencv_svm_hog\\Resource\\train_images\\airplanes\\image_0015.jpg", "E:\\opencv_svm_hog\\Resource\\train_images\\airplanes\\image_0016.jpg", "E:\\opencv_svm_hog\\Resource\\train_images\\airplanes\\image_0017.jpg", "E:\\opencv_svm_hog\\Resource\\train_images\\airplanes\\image_0018.jpg", "E:\\opencv_svm_hog\\Resource\\train_images\\airplanes\\image_0019.png", "E:\\opencv_svm_hog\\Resource\\train_images\\airplanes\\image_0020.jpg", "E:\\opencv_svm_hog\\Resource\\train_images\\airplanes\\image_0021.jpg", "E:\\opencv_svm_hog\\Resource\\train_images\\airplanes\\image_0022.jpg", "E:\\opencv_svm_hog\\Resource\\train_images\\airplanes\\image_0023.jpg", "E:\\opencv_svm_hog\\Resource\\train_images\\airplanes\\image_0024.jpg", "E:\\opencv_svm_hog\\Resource\\train_images\\airplanes\\image_0025.jpg", "E:\\opencv_svm_hog\\Resource\\train_images\\airplanes\\image_0026.jpg", "E:\\opencv_svm_hog\\Resource\\train_images\\airplanes\\image_0027.jpg", "E:\\opencv_svm_hog\\Resource\\train_images\\airplanes\\image_0028.jpg", "E:\\opencv_svm_hog\\Resource\\train_images\\airplanes\\image_0029.jpg", "E:\\opencv_svm_hog\\Resource\\train_images\\airplanes\\image_0030.jpg", "E:\\opencv_svm_hog\\Resource\\train_images\\airplanes\\image_0032.jpg", "E:\\opencv_svm_hog\\Resource\\train_images\\airplanes\\image_0033.jpg", "E:\\opencv_svm_hog\\Resource\\train_images\\airplanes\\image_0034.jpg", "E:\\opencv_svm_hog\\Resource\\train_images\\airplanes\\image_0035.jpg", "E:\\opencv_svm_hog\\Resource\\train_images\\airplanes\\image_0036.jpg", "E:\\opencv_svm_hog\\Resource\\train_images\\airplanes\\image_0037.jpg", "E:\\opencv_svm_hog\\Resource\\train_images\\airplanes\\image_0039.jpg", "E:\\opencv_svm_hog\\Resource\\train_images\\airplanes\\image_0040.jpg", "E:\\opencv_svm_hog\\Resource\\train_images\\airplanes\\image_0041.jpg", "E:\\opencv_svm_hog\\Resource\\train_images\\airplanes\\image_0042.jpg", "E:\\opencv_svm_hog\\Resource\\train_images\\airplanes\\image_0043.jpg", "E:\\opencv_svm_hog\\Resource\\train_images\\airplanes\\image_0044.jpg", "E:\\opencv_svm_hog\\Resource\\train_images\\airplanes\\image_0045.jpg", "E:\\opencv_svm_hog\\Resource\\train_images\\airplanes\\image_0046.jpg", "E:\\opencv_svm_hog\\Resource\\train_images\\airplanes\\image_0047.jpg", "E:\\opencv_svm_hog\\Resource\\train_images\\airplanes\\image_0048.jpg", "E:\\opencv_svm_hog\\Resource\\train_images\\airplanes\\image_0049.jpg", "E:\\opencv_svm_hog\\Resource\\train_images\\airplanes\\image_0050.jpg"], "type": 1}, "sunflower": {"list": ["E:\\opencv_svm_hog\\Resource\\train_images\\sunflower\\image_0001.jpg", "E:\\opencv_svm_hog\\Resource\\train_images\\sunflower\\image_0002.jpg", "E:\\opencv_svm_hog\\Resource\\train_images\\sunflower\\image_0003.jpg", "E:\\opencv_svm_hog\\Resource\\train_images\\sunflower\\image_0007.jpg", "E:\\opencv_svm_hog\\Resource\\train_images\\sunflower\\image_0008.jpg", "E:\\opencv_svm_hog\\Resource\\train_images\\sunflower\\image_0009.jpg", "E:\\opencv_svm_hog\\Resource\\train_images\\sunflower\\image_0010.jpg", "E:\\opencv_svm_hog\\Resource\\train_images\\sunflower\\image_0011.jpg", "E:\\opencv_svm_hog\\Resource\\train_images\\sunflower\\image_0012.jpg", "E:\\opencv_svm_hog\\Resource\\train_images\\sunflower\\image_0013.jpg", "E:\\opencv_svm_hog\\Resource\\train_images\\sunflower\\image_0014.jpg", "E:\\opencv_svm_hog\\Resource\\train_images\\sunflower\\image_0015.jpg", "E:\\opencv_svm_hog\\Resource\\train_images\\sunflower\\image_0016.jpg", "E:\\opencv_svm_hog\\Resource\\train_images\\sunflower\\image_0017.jpg", "E:\\opencv_svm_hog\\Resource\\train_images\\sunflower\\image_0018.jpg", "E:\\opencv_svm_hog\\Resource\\train_images\\sunflower\\image_0019.jpg", "E:\\opencv_svm_hog\\Resource\\train_images\\sunflower\\image_0020.jpg", "E:\\opencv_svm_hog\\Resource\\train_images\\sunflower\\image_0021.jpg", "E:\\opencv_svm_hog\\Resource\\train_images\\sunflower\\image_0022.jpg", "E:\\opencv_svm_hog\\Resource\\train_images\\sunflower\\image_0023.jpg", "E:\\opencv_svm_hog\\Resource\\train_images\\sunflower\\image_0024.jpg", "E:\\opencv_svm_hog\\Resource\\train_images\\sunflower\\image_0025.jpg", "E:\\opencv_svm_hog\\Resource\\train_images\\sunflower\\image_0026.jpg", "E:\\opencv_svm_hog\\Resource\\train_images\\sunflower\\image_0027.jpg", "E:\\opencv_svm_hog\\Resource\\train_images\\sunflower\\image_0028.jpg", "E:\\opencv_svm_hog\\Resource\\train_images\\sunflower\\image_0030.jpg", "E:\\opencv_svm_hog\\Resource\\train_images\\sunflower\\image_0031.jpg", "E:\\opencv_svm_hog\\Resource\\train_images\\sunflower\\image_0032.jpg", "E:\\opencv_svm_hog\\Resource\\train_images\\sunflower\\image_0033.jpg", "E:\\opencv_svm_hog\\Resource\\train_images\\sunflower\\image_0034.jpg", "E:\\opencv_svm_hog\\Resource\\train_images\\sunflower\\image_0035.jpg", "E:\\opencv_svm_hog\\Resource\\train_images\\sunflower\\image_0036.jpg", "E:\\opencv_svm_hog\\Resource\\train_images\\sunflower\\image_0037.jpg", "E:\\opencv_svm_hog\\Resource\\train_images\\sunflower\\image_0038.jpg", "E:\\opencv_svm_hog\\Resource\\train_images\\sunflower\\image_0039.jpg", "E:\\opencv_svm_hog\\Resource\\train_images\\sunflower\\image_0040.jpg", "E:\\opencv_svm_hog\\Resource\\train_images\\sunflower\\image_0041.jpg", "E:\\opencv_svm_hog\\Resource\\train_images\\sunflower\\image_0042.jpg", "E:\\opencv_svm_hog\\Resource\\train_images\\sunflower\\image_0043.jpg", "E:\\opencv_svm_hog\\Resource\\train_images\\sunflower\\image_0044.jpg", "E:\\opencv_svm_hog\\Resource\\train_images\\sunflower\\image_0045.jpg", "E:\\opencv_svm_hog\\Resource\\train_images\\sunflower\\image_0046.jpg", "E:\\opencv_svm_hog\\Resource\\train_images\\sunflower\\image_0047.jpg", "E:\\opencv_svm_hog\\Resource\\train_images\\sunflower\\image_0048.jpg", "E:\\opencv_svm_hog\\Resource\\train_images\\sunflower\\image_0049.jpg", "E:\\opencv_svm_hog\\Resource\\train_images\\sunflower\\image_0050.jpg"], "type": 5}}